Metadata-Version: 2.1
Name: topsis-Ananya-102017024
Version: 0.0.1
Summary: This program uses command line arguments to implement Topsis : a Multi-Criteria Decision Ananlysis (MCDA) method
Home-page: UNKNOWN
Author: Ananya Thomas
Author-email: ananyathomas10@gmail.com
License: UNKNOWN
Keywords: python,TOPSIS,MCDA,MCDM,predictive analytics,statistics
Platform: UNKNOWN
Classifier: Intended Audience :: Information Technology
Classifier: Intended Audience :: Education
Classifier: Intended Audience :: Science/Research
Classifier: Programming Language :: Python :: 3
Classifier: License :: OSI Approved :: MIT License
Classifier: Operating System :: OS Independent
Requires-Python: >=3.5
License-File: LICENSE.txt
